ujeebu_python/__init__.py
ujeebu_python/ujeebu_python.py
ujeebu_python-0.1.5.dist-info/licenses/AUTHORS.rst
ujeebu_python-0.1.5.dist-info/licenses/LICENSE
ujeebu_python-0.1.5.dist-info/METADATA
ujeebu_python-0.1.5.dist-info/WHEEL
ujeebu_python-0.1.5.dist-info/top_level.txt
ujeebu_python-0.1.5.dist-info/RECORD
